Workbook

Sheet 工时明细
A1: XiAiPet 宠物烘焙 - 开发费用工时统计表（完整补充版）
A2: 统计口径：从需求开始开发到6.10准上线状态 | B2: 统计口径：从 Codex session 019d96ca-adcb-7981-9525-eb33739d8118 开始，纳入 xiaipet 工作区后续产品开发、迁移、修复和验证；不纳入本次费用表生成会话。 | C2: 统计口径：从 Codex session 019d96ca-adcb-7981-9525-eb33739d8118 开始，纳入 xiaipet 工作区后续产品开发、迁移、修复和验证；不纳入本次费用表生成会话。 | D2: 统计口径：从 Codex session 019d96ca-adcb-7981-9525-eb33739d8118 开始，纳入 xiaipet 工作区后续产品开发、迁移、修复和验证；不纳入本次费用表生成会话。 | E2: 统计口径：从 Codex session 019d96ca-adcb-7981-9525-eb33739d8118 开始，纳入 xiaipet 工作区后续产品开发、迁移、修复和验证；不纳入本次费用表生成会话。 | F2: 统计口径：从 Codex session 019d96ca-adcb-7981-9525-eb33739d8118 开始，纳入 xiaipet 工作区后续产品开发、迁移、修复和验证；不纳入本次费用表生成会话。 | G2: 统计口径：从 Codex session 019d96ca-adcb-7981-9525-eb33739d8118 开始，纳入 xiaipet 工作区后续产品开发、迁移、修复和验证；不纳入本次费用表生成会话。 | H2: 统计口径：从 Codex session 019d96ca-adcb-7981-9525-eb33739d8118 开始，纳入 xiaipet 工作区后续产品开发、迁移、修复和验证；不纳入本次费用表生成会话。 | J2: 费用统计 | K2: 费用统计
J3: 工时单价 | K3: 65
A4: 开始时间 | B4: 结束时间 | C4: 工作内容 | D4: 工作类型 | E4: 来源会话ID | F4: 工作包/阶段 | G4: 开发工时 | H4: 小计费用 | J4: 总开发工时 | K4: =SUM(G5:G79) -> 832
A5: 2026-04-16 22:55 | B5: 2026-04-17 07:02 | C5: Phase 2 验收推进与 Phase 3/4 工作流衔接：核对商品发现链路状态，进入购物车、个人中心、地址和宠物资料开发阶段。 | D5: 讨论需求 | E5: 019d96ca-adcb-7981-9525-eb33739d8118 | F5: Phase 2 验收 / Phase 3-4 启动 | G5: 3 | H5: =G5*$K$3 -> 195 | J5: 开发费用合计 | K5: =K3*K4 -> 54080
A6: 2026-04-16 22:55 | B6: 2026-04-17 07:02 | C6: 购物车与规格选择设计：定义 cart row 身份、规格切换、库存上限、跨页面数量同步、结算入口边界。 | D6: 设计 | E6: 019d96ca-adcb-7981-9525-eb33739d8118 | F6: Phase 3 Cart State | G6: 6 | H6: =G6*$K$3 -> 390 | J6: 来源会话数 | K6: 127
A7: 2026-04-16 22:55 | B7: 2026-04-17 07:02 | C7: 购物车状态中心开发：共享 cart service、列表/搜索/详情加购、规格弹层、购物车页选中/清空/删除、结算占位路由。 | D7: 开发 | E7: 019d96ca-adcb-7981-9525-eb33739d8118 | F7: Phase 3 Cart State | G7: 24 | H7: =G7*$K$3 -> 1560 | J7: 计费明细行数 | K7: 75
A8: 2026-04-16 22:55 | B8: 2026-04-17 07:02 | C8: 购物车链路验证：cart service、discovery-cart、页面路由、规格切换与库存约束测试。 | D8: 测试 | E8: 019d96ca-adcb-7981-9525-eb33739d8118 | F8: Phase 3 Cart State | G8: 7 | H8: =G8*$K$3 -> 455 | J8: 起始会话 | K8: 019d96ca-adcb-7981-9525-eb33739d8118
A9: 2026-04-16 22:55 | B9: 2026-04-17 07:02 | C9: 个人中心与订单前上下文设计：资料、手机号绑定、同城/快递地址、宠物资料、余额流水、结算选择契约。 | D9: 设计 | E9: 019d96ca-adcb-7981-9525-eb33739d8118 | F9: Phase 4 Account/Pets/Address | G9: 7 | H9: =G9*$K$3 -> 455
A10: 2026-04-16 22:55 | B10: 2026-04-17 07:02 | C10: 个人中心、地址、宠物与余额页面开发：profile hub/detail、address list/form、pet list/form、balance ledger、checkout 回填链路。 | D10: 开发 | E10: 019d96ca-adcb-7981-9525-eb33739d8118 | F10: Phase 4 Account/Pets/Address | G10: 28 | H10: =G10*$K$3 -> 1820 | J10: 工作类型 | K10: 工时
A11: 2026-04-16 22:55 | B11: 2026-04-17 07:02 | C11: 个人中心上下文验证：profile/address/pet/balance 服务测试、页面测试、结算选择回归。 | D11: 测试 | E11: 019d96ca-adcb-7981-9525-eb33739d8118 | F11: Phase 4 Account/Pets/Address | G11: 8 | H11: =G11*$K$3 -> 520 | J11: 讨论需求 | K11: =SUMIF(D5:D79,"讨论需求",G5:G79) -> 34
A12: 2026-04-17 07:01 | B12: 2026-04-17 10:48 | C12: Phase 5 结算闭环需求确认：三种履约方式、预约时间、地址/电话/宠物/备注、支付后订单闭环。 | D12: 讨论需求 | E12: 019d9887-8166-70d3-be53-16d020d7ed1c | F12: Phase 5 Checkout/Payment/Orders | G12: 3 | H12: =G12*$K$3 -> 195 | J12: 设计 | K12: =SUMIF(D5:D79,"设计",G5:G79) -> 126
A13: 2026-04-17 07:01 | B13: 2026-04-17 10:48 | C13: 结算、支付与订单设计：配送费、订单快照、余额/微信支付边界、支付确认、订单列表/详情模型。 | D13: 设计 | E13: 019d9887-8166-70d3-be53-16d020d7ed1c | F13: Phase 5 Checkout/Payment/Orders | G13: 8 | H13: =G13*$K$3 -> 520 | J13: 开发 | K13: =SUMIF(D5:D79,"开发",G5:G79) -> 517
A14: 2026-04-17 07:01 | B14: 2026-04-17 10:48 | C14: 结算支付订单开发：checkout 服务和页面、订单提交、createOrder/createPayment/confirmPayment、orders/order-detail 页面、持久化订单与余额支付事务骨架。 | D14: 开发 | E14: 019d9887-8166-70d3-be53-16d020d7ed1c | F14: Phase 5 Checkout/Payment/Orders | G14: 32 | H14: =G14*$K$3 -> 2080 | J14: 测试 | K14: =SUMIF(D5:D79,"测试",G5:G79) -> 155
A15: 2026-04-17 07:01 | B15: 2026-04-17 10:48 | C15: 结算订单验证：共享定价/订单类型、客户小程序、云函数订单与支付测试，typecheck/build。 | D15: 测试 | E15: 019d9887-8166-70d3-be53-16d020d7ed1c | F15: Phase 5 Checkout/Payment/Orders | G15: 10 | H15: =G15*$K$3 -> 650
A16: 2026-04-17 10:47 | B16: 2026-04-17 22:20 | C16: Phase 6 商户端运营范围讨论：订单、品类/商品、用户余额、运行时配置、商户工作台和权限边界。 | D16: 讨论需求 | E16: 019d9956-433e-7e30-bb88-dab3a1de6b02 | F16: Phase 6 讨论与规划 | G16: 6 | H16: =G16*$K$3 -> 390
A17: 2026-04-17 15:08 | B17: 2026-04-17 22:20 | C17: Phase 6 研究与 UI 契约：微信内轻量工作台、订单列表/详情、商品三步编辑、用户余额抽屉、分区运营配置、按钮文案与首页焦点修正。 | D17: 设计 | E17: 019d9a45-03de-7d40-ab04-d44a23eb5d60 | F17: Phase 6 UI/UX Spec | G17: 14 | H17: =G17*$K$3 -> 910
A18: 2026-04-17 15:35 | B18: 2026-04-17 22:20 | C18: 商户端共享契约开发：履约状态、手工结算审计、品类/商品 schema、组合定价、用户搜索/余额调整、运行时配置固定分区。 | D18: 开发 | E18: 019d9a5d-ee70-7321-9da1-a05bf0c994af | F18: Phase 6 Shared Contracts | G18: 24 | H18: =G18*$K$3 -> 1560
A19: 2026-04-17 15:35 | B19: 2026-04-17 22:20 | C19: 商户端后端接口开发：merchant orders、order detail/status、category/product CRUD、user search/balance adjust、runtime config handlers、索引和安全规则。 | D19: 开发 | E19: 019d9bc2-3b83-7fb1-b812-673dd9ffb66e | F19: Phase 6 Backend Functions | G19: 34 | H19: =G19*$K$3 -> 2210
A20: 2026-04-17 15:35 | B20: 2026-04-18 06:20 | C20: 商户端前端页面开发：订单列表/详情、品类管理、商品列表/三步编辑、用户搜索/详情、运行时配置、工作台入口和路由注册。 | D20: 开发 | E20: 019d9bc2-3b9d-7253-8a4b-d6da1f744cd7 | F20: Phase 6 Merchant Miniapp UI | G20: 42 | H20: =G20*$K$3 -> 2730
A21: 2026-04-17 15:35 | B21: 2026-04-18 06:20 | C21: 用户端运行时配置与余额展示接入：home banner、checkout 店铺/提示/配送说明、余额流水标准化文案。 | D21: 开发 | E21: 019d9bc2-3bbf-7431-a7c7-2bdb68f60870 | F21: Phase 6 Customer Runtime Wiring | G21: 12 | H21: =G21*$K$3 -> 780
A22: 2026-04-17 15:28 | B22: 2026-04-17 22:38 | C22: Phase 6 覆盖校验与修订：UI spec 校验、计划拆分、覆盖性验证、最终验收、图片持久化和路由校验。 | D22: 测试 | E22: 019d9a57-4c5a-7990-8aee-e9d4e2c48516 | F22: Phase 6 Review/Verification | G22: 18 | H22: =G22*$K$3 -> 1170
A23: 2026-04-19 14:42 | B23: 2026-04-20 15:34 | C23: 小程序视觉与导航优化设计：首页四按钮云图片展示、凸起订单 tabbar、page-nav-bar 透明异常、导航迁移检查。 | D23: 设计 | E23: 019da47a-0c35-7552-9acb-8de54718b126 | F23: Miniapp UI polish | G23: 4 | H23: =G23*$K$3 -> 260
A24: 2026-04-19 14:42 | B24: 2026-04-20 15:34 | C24: 小程序视觉与导航优化开发：替换首页入口图片引用、调整订单页 tabbar 样式、修复导航栏透明显示与页面适配。 | D24: 开发 | E24: 019da4c3-0399-7551-8fea-a15ece1244c5 | F24: Miniapp UI polish | G24: 12 | H24: =G24*$K$3 -> 780
A25: 2026-04-19 14:42 | B25: 2026-04-20 15:34 | C25: 小程序视觉导航验证：页面结构检查、样式回归、导航迁移检查。 | D25: 测试 | E25: 019da9d0-2824-7501-86e2-2463b318c8d2 | F25: Miniapp UI polish | G25: 4 | H25: =G25*$K$3 -> 260
A26: 2026-04-21 09:55 | B26: 2026-04-21 18:20 | C26: 购物车规格切换和页面重构需求复核：修正规格切换、库存合并、稳定重排、滑删和页面布局质量问题。 | D26: 讨论需求 | E26: 019dadbf-a31b-7e20-858d-e530774d11f6 | F26: Cart hardening | G26: 2 | H26: =G26*$K$3 -> 130
... A79: 2026-06-09 13:48 | B79: 2026-06-09 17:05 | C79: 商品规格与品类数量验证：API catalog/routes、客户 catalog service、后端统计 28/分页 20 回归、typecheck/build。 | D79: 测试 | E79: 019eab9a-c2a3-79f2-b265-083b64491662 | F79: Recent bug fixes | G79: 3 | H79: =G79*$K$3 -> 195

Sheet 费用汇总
A1: XiAiPet 宠物烘焙 - 开发费用汇总
A3: 项目 | B3: XiAiPet 宠物烘焙 | D3: 工作类型 | E3: 工时 | F3: 占比
A4: 统计来源 | B4: Codex session 019d96ca-adcb-7981-9525-eb33739d8118 起的 xiaipet 会话 + .planning 阶段摘要 | D4: 讨论需求 | E4: =工时明细!K11 -> 34 | F4: =E4/$B$7 -> 0.040865385
A5: 统计期间 | B5: 2026-04-16 至 2026-06-09 | D5: 设计 | E5: =工时明细!K12 -> 126 | F5: =E5/$B$7 -> 0.15144231
A6: 工时单价 | B6: =工时明细!K3 -> 65 | D6: 开发 | E6: =工时明细!K13 -> 517 | F6: =E6/$B$7 -> 0.62139423
A7: 总开发工时 | B7: =工时明细!K4 -> 832 | D7: 测试 | E7: =工时明细!K14 -> 155 | F7: =E7/$B$7 -> 0.18629808
A8: 开发费用合计 | B8: =工时明细!K5 -> 54080
A9: 来源会话数 | B9: =工时明细!K6 -> 127
A10: 计费说明 | B10: 排除本次费用表生成会话
A12: 费用说明 | B12: 费用说明 | C12: 费用说明 | D12: 费用说明 | E12: 费用说明 | F12: 费用说明
A13: 按照正常工价为150元/小时，给朋友做项目按照65元/小时前端 75元/小时后端，所有工作内容能落档的会被统计。目前只按照65元前端价格进行统计。 | B13: 本表将密集的子会话、review 会话和阶段执行结果合并为可向甲方说明的工作包。右侧总工时和费用均由明细自动汇总；如需调整单价，修改“工时明细”K3 即可自动重算。 | C13: 本表将密集的子会话、review 会话和阶段执行结果合并为可向甲方说明的工作包。右侧总工时和费用均由明细自动汇总；如需调整单价，修改“工时明细”K3 即可自动重算。 | D13: 本表将密集的子会话、review 会话和阶段执行结果合并为可向甲方说明的工作包。右侧总工时和费用均由明细自动汇总；如需调整单价，修改“工时明细”K3 即可自动重算。 | E13: 本表将密集的子会话、review 会话和阶段执行结果合并为可向甲方说明的工作包。右侧总工时和费用均由明细自动汇总；如需调整单价，修改“工时明细”K3 即可自动重算。 | F13: 本表将密集的子会话、review 会话和阶段执行结果合并为可向甲方说明的工作包。右侧总工时和费用均由明细自动汇总；如需调整单价，修改“工时明细”K3 即可自动重算。
A14: 本表将密集的子会话、review 会话和阶段执行结果合并为可向甲方说明的工作包。右侧总工时和费用均由明细自动汇总；如需调整单价，修改“工时明细”K3 即可自动重算。 | B14: 本表将密集的子会话、review 会话和阶段执行结果合并为可向甲方说明的工作包。右侧总工时和费用均由明细自动汇总；如需调整单价，修改“工时明细”K3 即可自动重算。 | C14: 本表将密集的子会话、review 会话和阶段执行结果合并为可向甲方说明的工作包。右侧总工时和费用均由明细自动汇总；如需调整单价，修改“工时明细”K3 即可自动重算。 | D14: 本表将密集的子会话、review 会话和阶段执行结果合并为可向甲方说明的工作包。右侧总工时和费用均由明细自动汇总；如需调整单价，修改“工时明细”K3 即可自动重算。 | E14: 本表将密集的子会话、review 会话和阶段执行结果合并为可向甲方说明的工作包。右侧总工时和费用均由明细自动汇总；如需调整单价，修改“工时明细”K3 即可自动重算。 | F14: 本表将密集的子会话、review 会话和阶段执行结果合并为可向甲方说明的工作包。右侧总工时和费用均由明细自动汇总；如需调整单价，修改“工时明细”K3 即可自动重算。
A15: 本表将密集的子会话、review 会话和阶段执行结果合并为可向甲方说明的工作包。右侧总工时和费用均由明细自动汇总；如需调整单价，修改“工时明细”K3 即可自动重算。 | B15: 本表将密集的子会话、review 会话和阶段执行结果合并为可向甲方说明的工作包。右侧总工时和费用均由明细自动汇总；如需调整单价，修改“工时明细”K3 即可自动重算。 | C15: 本表将密集的子会话、review 会话和阶段执行结果合并为可向甲方说明的工作包。右侧总工时和费用均由明细自动汇总；如需调整单价，修改“工时明细”K3 即可自动重算。 | D15: 本表将密集的子会话、review 会话和阶段执行结果合并为可向甲方说明的工作包。右侧总工时和费用均由明细自动汇总；如需调整单价，修改“工时明细”K3 即可自动重算。 | E15: 本表将密集的子会话、review 会话和阶段执行结果合并为可向甲方说明的工作包。右侧总工时和费用均由明细自动汇总；如需调整单价，修改“工时明细”K3 即可自动重算。 | F15: 本表将密集的子会话、review 会话和阶段执行结果合并为可向甲方说明的工作包。右侧总工时和费用均由明细自动汇总；如需调整单价，修改“工时明细”K3 即可自动重算。
A16: 本表将密集的子会话、review 会话和阶段执行结果合并为可向甲方说明的工作包。右侧总工时和费用均由明细自动汇总；如需调整单价，修改“工时明细”K3 即可自动重算。 | B16: 本表将密集的子会话、review 会话和阶段执行结果合并为可向甲方说明的工作包。右侧总工时和费用均由明细自动汇总；如需调整单价，修改“工时明细”K3 即可自动重算。 | C16: 本表将密集的子会话、review 会话和阶段执行结果合并为可向甲方说明的工作包。右侧总工时和费用均由明细自动汇总；如需调整单价，修改“工时明细”K3 即可自动重算。 | D16: 本表将密集的子会话、review 会话和阶段执行结果合并为可向甲方说明的工作包。右侧总工时和费用均由明细自动汇总；如需调整单价，修改“工时明细”K3 即可自动重算。 | E16: 本表将密集的子会话、review 会话和阶段执行结果合并为可向甲方说明的工作包。右侧总工时和费用均由明细自动汇总；如需调整单价，修改“工时明细”K3 即可自动重算。 | F16: 本表将密集的子会话、review 会话和阶段执行结果合并为可向甲方说明的工作包。右侧总工时和费用均由明细自动汇总；如需调整单价，修改“工时明细”K3 即可自动重算。
A17: 本表将密集的子会话、review 会话和阶段执行结果合并为可向甲方说明的工作包。右侧总工时和费用均由明细自动汇总；如需调整单价，修改“工时明细”K3 即可自动重算。 | B17: 本表将密集的子会话、review 会话和阶段执行结果合并为可向甲方说明的工作包。右侧总工时和费用均由明细自动汇总；如需调整单价，修改“工时明细”K3 即可自动重算。 | C17: 本表将密集的子会话、review 会话和阶段执行结果合并为可向甲方说明的工作包。右侧总工时和费用均由明细自动汇总；如需调整单价，修改“工时明细”K3 即可自动重算。 | D17: 本表将密集的子会话、review 会话和阶段执行结果合并为可向甲方说明的工作包。右侧总工时和费用均由明细自动汇总；如需调整单价，修改“工时明细”K3 即可自动重算。 | E17: 本表将密集的子会话、review 会话和阶段执行结果合并为可向甲方说明的工作包。右侧总工时和费用均由明细自动汇总；如需调整单价，修改“工时明细”K3 即可自动重算。 | F17: 本表将密集的子会话、review 会话和阶段执行结果合并为可向甲方说明的工作包。右侧总工时和费用均由明细自动汇总；如需调整单价，修改“工时明细”K3 即可自动重算。

Sheet 会话来源
A1: 会话来源
A2: 从起始 session 开始筛选 工作可以落档有迹可循的工作记录。 | B2: 从起始 session 开始筛选 cwd 为 xiaipet 的本地 Codex 会话；“是否计费来源”用于排除本次费用表生成会话。 | C2: 从起始 session 开始筛选 cwd 为 xiaipet 的本地 Codex 会话；“是否计费来源”用于排除本次费用表生成会话。 | D2: 从起始 session 开始筛选 cwd 为 xiaipet 的本地 Codex 会话；“是否计费来源”用于排除本次费用表生成会话。 | E2: 从起始 session 开始筛选 cwd 为 xiaipet 的本地 Codex 会话；“是否计费来源”用于排除本次费用表生成会话。
A4: 会话时间 | B4: 会话ID | C4: 线程标题 | D4: 是否计费来源 | E4: 本地日志
A5: 2026-04-16 22:55 | B5: 019d96ca-adcb-7981-9525-eb33739d8118 | C5: Advance GSD workflow / phase3 4 | D5: 是 | E5: ~/.codex/sessions/2026/04/16/rollout-2026-04-16T22-55-58-019d96ca-adcb-7981-9525-eb33739d8118.jsonl
A6: 2026-04-17 07:01 | B6: 019d9887-8166-70d3-be53-16d020d7ed1c | C6: 继续推进 phase 5 实施任务'} / phase 5 | D6: 是 | E6: ~/.codex/sessions/2026/04/17/rollout-2026-04-17T07-01-50-019d9887-8166-70d3-be53-16d020d7ed1c.jsonl
A7: 2026-04-17 10:47 | B7: 019d9956-433e-7e30-bb88-dab3a1de6b02 | C7: Discuss phase 6 batch / phase 6 | D7: 是 | E7: ~/.codex/sessions/2026/04/17/rollout-2026-04-17T10-47-40-019d9956-433e-7e30-bb88-dab3a1de6b02.jsonl
A8: 2026-04-17 15:08 | B8: 019d9a45-03de-7d40-ab04-d44a23eb5d60 | C8: Research phase 6 planning | D8: 是 | E8: ~/.codex/sessions/2026/04/17/rollout-2026-04-17T15-08-27-019d9a45-03de-7d40-ab04-d44a23eb5d60.jsonl
A9: 2026-04-17 15:22 | B9: 019d9a52-537d-7600-9a39-256b7eb144a4 | C9: 创建第6阶段商户运营与运行配置UI设计契约 | D9: 是 | E9: ~/.codex/sessions/2026/04/17/rollout-2026-04-17T15-22-59-019d9a52-537d-7600-9a39-256b7eb144a4.jsonl
A10: 2026-04-17 15:28 | B10: 019d9a57-4c5a-7990-8aee-e9d4e2c48516 | C10: Validate Phase 6 UI spec | D10: 是 | E10: ~/.codex/sessions/2026/04/17/rollout-2026-04-17T15-28-25-019d9a57-4c5a-7990-8aee-e9d4e2c48516.jsonl
A11: 2026-04-17 15:30 | B11: 019d9a59-2657-7f62-bb6d-6bba200f128c | C11: 修正 UI-SPEC 按钮文案与首页焦点 | D11: 是 | E11: ~/.codex/sessions/2026/04/17/rollout-2026-04-17T15-30-27-019d9a59-2657-7f62-bb6d-6bba200f128c.jsonl
A12: 2026-04-17 15:32 | B12: 019d9a5a-a135-7362-ac12-fb4817adca4c | C12: Validate phase 6 UI spec | D12: 是 | E12: ~/.codex/sessions/2026/04/17/rollout-2026-04-17T15-32-04-019d9a5a-a135-7362-ac12-fb4817adca4c.jsonl
A13: 2026-04-17 15:35 | B13: 019d9a5d-ee70-7321-9da1-a05bf0c994af | C13: Execute phase 06 plans | D13: 是 | E13: ~/.codex/sessions/2026/04/17/rollout-2026-04-17T15-35-40-019d9a5d-ee70-7321-9da1-a05bf0c994af.jsonl
A14: 2026-04-17 15:45 | B14: 019d9a67-1850-7970-b796-5369f0d824b6 | C14: (未命名会话) | D14: 是 | E14: ~/.codex/sessions/2026/04/17/rollout-2026-04-17T15-45-40-019d9a67-1850-7970-b796-5369f0d824b6.jsonl
... A131: 2026-06-10 09:13 | B131: 019eaf17-42d1-7760-a807-ddbc37e50146 | C131: 生成开发工时费用表 | D131: 否-费用表生成会话 | E131: ~/.codex/sessions/2026/06/10/rollout-2026-06-10T09-13-17-019eaf17-42d1-7760-a807-ddbc37e50146.jsonl

Sheet 阶段摘要
A1: 阶段摘要
A3: 阶段 | B3: 英文标题 | C3: 纳入费用的主要内容 | D3: 规划摘要目录
A4: Phase 3 | B4: Cart State and Product Selection | C4: 购物车、规格选择、快速加购、购物车页与结算入口 | D4: .planning/phases/03-cart-state-and-product-selection
A5: Phase 4 | B5: Account, Pets and Address Context | C5: 个人中心、地址、宠物、余额流水和订单前上下文 | D5: .planning/phases/04-account-pets-and-address-context
A6: Phase 5 | B6: Checkout, Payment and Orders | C6: 确认订单、配送费、支付、订单列表/详情、订单持久化 | D6: .planning/phases/05-checkout-payment-and-orders
A7: Phase 6 | B7: Merchant Operations and Runtime Config | C7: 商户订单、品类商品、用户余额、运营配置、工作台、小票打印 | D7: .planning/phases/06-merchant-operations-and-runtime-config
A8: Phase 7 | B8: Node API Foundation and ECS Deployment Runway | C8: 统一 Node API、配置、日志、Docker、ECS 部署基座 | D8: .planning/phases/07-node-api-foundation-and-ecs-deployment-runway
A9: Phase 8 | B9: MySQL Data Model and Migration Pipeline | C9: Prisma/MySQL/RDS、seed、repository、事务和 CloudBase 导入验证 | D9: .planning/phases/08-mysql-data-model-and-migration-pipeline
A10: Phase 9 | B10: HTTP API Parity for Unified Backend | C10: 用户/商户/订单/支付/商品/配置/打印 HTTP API 等价实现 | D10: .planning/phases/09-http-api-parity-for-unified-backend
A11: Phase 10 | B11: Mini Program API Client Migration | C11: 客户/商户小程序服务从 CloudBase 迁移到统一 HTTP API client | D11: .planning/phases/10-mini-program-api-client-migration
A12: Phase 11 | B12: OSS Asset Migration and Upload Flow | C12: OSS 上传、图片迁移、商品/Banner 资产读取与兼容 | D12: .planning/phases/11-oss-asset-migration-and-upload-flow
A13: Phase 12 | B13: Production Cutover Security and Regression Verification | C13: 生产域名、部署、安全、冒烟、回归、回滚与 CloudBase 退役闸门 | D13: .planning/phases/12-production-cutover-security-and-regression-verification
